app/__init__.py
app/api/__init__.py
app/api/annotation.py
app/api/course.py
app/api/graph.py
app/api/semantic.py
app/api/vector.py
app/main/__init__.py
app/main/routes.py
models/__init__.py
models/annotation.py
models/course.py
models/database.py
models/document.py
models/user.py
services/__init__.py
services/annotation_service.py
services/llm_service.py
services/semantic_service.py
services/vector_service.py
bio_knowledge_graph-1.1.0.dist-info/METADATA
bio_knowledge_graph-1.1.0.dist-info/WHEEL
bio_knowledge_graph-1.1.0.dist-info/top_level.txt
bio_knowledge_graph-1.1.0.dist-info/RECORD
