Metadata-Version: 2.4
Name: bio_knowledge_graph
Version: 1.1.0
Summary: A Chinese relation extraction data utility toolkit based on CasRel model
Home-page: https://github.com/yuyanhong/bio_knowledge_graph
Author: DT.L
Classifier: Programming Language :: Python :: 3
Classifier: License :: OSI Approved :: MIT License
Classifier: Operating System :: OS Independent
Requires-Python: >=3.7
Requires-Dist: torch
Requires-Dist: transformers>=4.0.0
Dynamic: author
Dynamic: classifier
Dynamic: description
Dynamic: description-content-type
Dynamic: home-page
Dynamic: requires-dist
Dynamic: requires-python
Dynamic: summary
